docutils_html5/__init__.py
docutils_html5_writer-1.0.3.dist-info/DESCRIPTION.rst
docutils_html5_writer-1.0.3.dist-info/METADATA
docutils_html5_writer-1.0.3.dist-info/RECORD
docutils_html5_writer-1.0.3.dist-info/WHEEL
docutils_html5_writer-1.0.3.dist-info/metadata.json
docutils_html5_writer-1.0.3.dist-info/top_level.txt
