Metadata-Version: 2.0
Name: docutils-html5-writer
Version: 1.0.3
Summary: UNKNOWN
Home-page: UNKNOWN
Author: James H. Fisher, Kozea
Author-email: UNKNOWN
License: public domain
Platform: UNKNOWN
Requires-Dist: docutils
Requires-Dist: html5lib
Requires-Dist: lxml
Requires-Dist: python-dateutil
